{
  "lema": "CRISTALIZAR.",
  "categoria_gramatical": "v.",
  "introduccion": "--> v. Reducir á cristales, como se hace por medio de ciertas operaciones químicas, con las sustancias salinas, térreas, metálicas y otras ( trans .). — α ) «Este procedimiento [de los fundentes] se considera como uno de los medios más enérgicos de cristalización, habiendo llegado á obtener algunos físicos y mineralogistas, mediante él, cristalizar la esmeralda, topacio, zafiro, etc.» La creación , 8, p. 5 1 . — β ) Refl. Reducirse á cristales. — α α ) Con en , para expresar la forma de los cristales. «Cristalizarse en prismas.» Acad . Dicc. — γ ) Intrans. Tomar ciertos cuerpos formas geométricas al pasar del estado líquido al sólido. Con en, para expresar la forma de los cristales. «CristaIizar en prismas.» Acad. Gram . «La pirita de hierro y la boracita --- cristalizan en cubos.» La creacion , 8, p. 7 2 ). «El cobre fundido cristaliza en prismas rectangulares rectos.» Ib . — δ ) Part. «Además va en el cesto una pieza que me enviaron de Mahón con el nombre de madrépora, y no es otra cosa que una planta marina petrificada, ó más bien cristalizada por medio de algunas sales aglomeradas sobre ella.» Jovell. Corresp. con Posada (R. 50. 248 2 ). — α α ) Con en. «Unas veces se presenta [la cal carbonatada de Haüy] cristalizada en romboedros del sistema romboédrico, y otras en prismas exagonales que corresponden al prisma rectangular recto.» La creación , 8, p. 7 2 .",
  "acepciones": [
    {
      "id": "Etim.",
      "definicion": "Fr. c ristalliser, de donde lo hemos tomado; derivado de cristal .",
      "ejemplos_citas": [],
      "subacepciones": []
    },
    {
      "id": "Ortogr.",
      "definicion": "Antes de e se escribe c : cristalicen. \u0000",
      "ejemplos_citas": [],
      "subacepciones": []
    }
  ],
  "etimologia": ""
}