{
  "lema": "DIVERSAMENTE.",
  "categoria_gramatical": "adv",
  "introduccion": "-->adv . De manera diversa, con diversidad. — α ). «Las flores, á los ojos ofreciendo | Diversidad extraña de pintura, | Diversamente así estaban oliendo.» Garcil. égl . 2 (R. 32. 9 2 ). «Los mismos que sentían diversamente eran los primeros á besalle la mano y hacelle todo homenaje.» Mariana , Hist. Esp . 18. 9 (R. 31. 14 1 ). «Como son diversos los objetos y diversa la fortuna de los amadores, sin duda alguna diversamente se desea.» Cerv. Gol . 4 (R. 1. 56 1 ). «Si pudiera yo decirte | La verdad; si persuadirte, | Señora, y desengañarte, | Oyeras diversamente | De mi agraviada opinión | La cuerda satisfacción.» Tirso , La ventura con el nombre , 3. 7 (R. 5. 535 1 ). «De donde nacen tan desconformes opiniones y pareceres como hay en los hombres, concibiendo cada uno diversamente lo que oye ó ve.» Saav. Rep . (R. 25. 399 2 ). — β ) Con de , para denotar la divergencia entre dos acciones ó sus circunstancias. «Cornelio Nepote escribe muy diversamente de lo que he dicho de aqueste Dionisio.» Comend. Griego , Lab . 228 (80 2 ). «Muchas [cosas] suceden diversamente en el hecho de lo que se presuponía antes.» Saav. Emp . 46 (R. 25. 117 2 ). «La risa procedente de las cosas medias, trae su origen y principio del engañar la expectación con respuestas y dichos inopinados, ó con fingir que se entienden los dichos ajenos diversamente de lo que significan.» Luzán , Poét . 2. 20 (1. 304). — γ ) Con que en frases elípticas. «Diversamente impera en los ánimos la costumbre que la ley.» Bello , Gram . § 369.",
  "acepciones": [
    {
      "id": "Etim.",
      "definicion": "Compuesto del adjetivo diverso y el sufijo modal mente . En el pasaje siguiente parece significar Difusamente:",
      "ejemplos_citas": [
        {
          "texto_cita": "«Yo, como iba historiando mi vida, no advertí que podría el ermitaño cansarse de oírme hablar tan diversamente; pero sucedióme bien.»",
          "autor": "Espinel",
          "referencia_obra": ", Escud. 2. 1 (R. 18. 427 2 ). \u0000"
        }
      ],
      "subacepciones": []
    }
  ],
  "etimologia": ""
}